[{"premises": ["Shuli arrived earlier than David, possibly with others in between.", "John entered later than Rina, possibly with others in between.", "Rina showed up later than David, possibly with others in between."], "possible_conclusions": [[["Shuli", "Rina"], "TRUE"], [["Shuli", "John"], "TRUE"], [["David", "John"], "TRUE"], [["Rina", "Shuli"], "FALSE"], [["John", "Shuli"], "FALSE"], [["John", "David"], "FALSE"]], "names": ["Shuli", "David", "Rina", "John"], "number_of_people": 4, "possible_arrangements": [["Shuli", "David", "Rina", "John"]]}, {"premises": ["Dylan showed up later than John, possibly with others in between.", "David arrived before John, possibly with others in between.", "David came after Rina, possibly with others in between."], "possible_conclusions": [[["Rina", "John"], "TRUE"], [["Rina", "Dylan"], "TRUE"], [["David", "Dylan"], "TRUE"], [["John", "Rina"], "FALSE"], [["Dylan", "Rina"], "FALSE"], [["Dylan", "David"], "FALSE"]], "names": ["Rina", "David", "John", "Dylan"], "number_of_people": 4, "possible_arrangements": [["Rina", "David", "John", "Dylan"]]}]