[{"premises": ["Emily entered later than Judith.", "Judith came earlier than John.", "Judith arrived after Dylan."], "possible_conclusions": [[["John", "Dylan"], "FALSE"], [["John", "Emily"], "UNABLE_TO_DETERMINE"], [["Dylan", "John"], "TRUE"], [["Dylan", "Emily"], "TRUE"], [["Emily", "John"], "UNABLE_TO_DETERMINE"], [["Emily", "Dylan"], "FALSE"]], "names": ["Judith", "John", "Dylan", "Emily"], "number_of_people": 4, "possible_arrangements": [["Dylan", "Judith", "Emily", "John"], ["Dylan", "Judith", "John", "Emily"]]}, {"premises": ["Moshe came earlier than David.", "Moshe arrived later than Judith.", "John showed up later than Judith."], "possible_conclusions": [[["David", "Judith"], "FALSE"], [["David", "John"], "UNABLE_TO_DETERMINE"], [["Moshe", "John"], "UNABLE_TO_DETERMINE"], [["Judith", "David"], "TRUE"], [["John", "David"], "UNABLE_TO_DETERMINE"], [["John", "Moshe"], "UNABLE_TO_DETERMINE"]], "names": ["David", "Moshe", "Judith", "John"], "number_of_people": 4, "possible_arrangements": [["Judith", "John", "Moshe", "David"], ["Judith", "Moshe", "David", "John"], ["Judith", "Moshe", "John", "David"]]}]